{
  "merchant_id": 2,
  "merchant_name": "AIMSKINZ LIMITED",
  "merchant_group": "SENDS",
  "company_name": "AIMSKINZ LIMITED",
  "kam": "ZHUKOVA, Olena",
  "contract_id": "01/08-01",
  "transaction_count": 0,
  "approved_count": 0,
  "declined_count": 0,
  "acceptance_rate": 0,
  "total_amount_eur": 0.0,
  "total_commission_eur": 0.0,
  "sale_count": 0,
  "sale_amount": 0.0,
  "payout_count": 0,
  "payout_amount": 0.0,
  "reversal_count": 0,
  "reversal_amount": 0.0,
  "first_transaction_date": "",
  "partners": [
    "SENDS"
  ],
  "currency_breakdown": []
}