{"transaction":{"transaction_id":"dd12b334-f480-4e55-8fb8-7a0591c35df9","status":"approved","transaction_status":"approved","type":"payment","transaction_type":"sale","created_date":"2025-12-04 17:39:52.176157 UTC","created_date_no_time":"2025-12-04","error_code":0,"error_message":"0","external_error_code":"0","external_error_message":"0"},"order_details":{"order_id":1456359885,"user_id":50750259,"item_id":4598,"amount":5.0,"amount_eur":5.0,"currency":"EUR","country":"DE","european_union":"EU","eea":"EEA","requisites_country":"DE"},"payment_method":{"card_brand_group":"Any","card_type":"Any","traffic_type_group":"openbanking","gate_name":"openbanking","gate_id":69,"gate_descriptor":"IN - Volt Skunlock Openbanking","main_requisite":"DE12100101788067236015"},"processing":{"processor_name":"Volt","processor_id":69,"proc_group":"Volt","acquirer_name":"Volt","endpoint_id":70051092,"descr_group":"skunlock","source":"GATE"},"merchant":{"merchant_id":405,"merchant_name":"Yougmedia B.V.","merchant":"Yougmedia B.V.","merchant_group":"Fonbet","company_id":190,"company_name":"Yougmedia B.V.","legal_entity_abb":"SKN","white_label_id":9,"kam":"Karolina"},"commission_fields":{"comission_eur":0.63,"transaction_comission":0.63,"fixed_eur":0.15,"fx_rate":1.0,"fx_date":"2025-12-04"},"cost_fields":{"base_eur":0.0375,"mdr":0.0075,"mdr_eur":0.0375,"agent_eur":null,"agent":null,"tax_reserved_eur":0.0029999999999999996,"tax_reserve_cost":0.0006,"settle_eur":null,"settlement":null,"trx":0.15},"other":{"rate_plan_id":"70051092_EUR_Open_Banking_EEA_WL_IN","running_sum":274853.82,"balance_mapping":"Volt - skunlock","mapping":"Germany"},"applied_plan":{"plan_key":"70051092_EUR_Open_Banking_EEA_WL_IN","operation_type":"incoming","payment_type":"apm","currency":"EUR","region":"EEA","apm_type":"open_banking","traffic_type":"openbanking","card_brand":null,"wl_percent":null,"fixed_fee":null,"exchange_fee_percent":null,"refund_fee":null,"payout_percent":null,"payout_fixed":null,"actual_eur":0.63,"actual_local":0.63,"effective_rate":9.6,"fixed_eur":0.15,"fixed_local":0.15,"fx_rate":1.0,"expected_eur":0.625,"expected_local":0.625,"plan_rate":2.5,"plan_fixed":0.5,"deviation_pct":0.8,"deviation_eur":0.005,"deviation_local":0.005},"deviation":{"actual":0.63,"calculated":0.625,"difference":0.0050000000000000044,"percent":0.8000000000000007,"effective_rate":9.6,"plan_rate":2.5,"actual_local":0.63,"expected_local":0.625,"deviation_local":0.005,"plan_fixed":0.5},"calculation":{"type":"incoming_eur","description":"Incoming (EUR)","formula":"((5.00 × 2.5%) + 0.50)","value":0.625,"formatted":"€0.62","steps":[{"label":"Amount (EUR)","value":5.0,"formatted":"€5.00"},{"label":"WL Rate (2.5%)","value":0.125,"formatted":"€0.12"},{"label":"Fixed Fee","value":0.5,"formatted":"€0.50"},{"label":"Total","value":0.625,"formatted":"€0.62"}],"effective_rate":2.6,"currency":"EUR","fx_rate":1.0,"value_local":0.625}}