{
  "transaction": {
    "transaction_id": "dd110d81-b79a-4732-8640-e3a9b27252be",
    "error_message": "0",
    "transaction_status": "approved",
    "created_date_no_time": "2025-11-26",
    "merchant_error_code": 0,
    "transaction_type": "sale",
    "type": "payment",
    "external_error_code": "0",
    "merchant_error_message": "0",
    "external_error_message": "0",
    "error_code": 0,
    "created_date": "2025-11-26 22:34:44.318918 UTC",
    "status": "approved"
  },
  "order_details": {
    "eea": "EEA",
    "country": "HU",
    "bin": 41659840,
    "running_sum": 1836206.93,
    "endpoint_id": 70050492,
    "gate_name": "card",
    "amount_eur": 261.79,
    "fx_date": "2025-11-26",
    "european_union": "EU",
    "card_brand": "VISA",
    "currency": "EUR",
    "fx_rate": 1.0,
    "requisites_bank": null,
    "card_brand_group": "Visa",
    "mapping": "Hungary",
    "amount": 261.79,
    "requisites_country": "HU",
    "traffic_type_group": "wl",
    "gate_descriptor": "IN - Euroexchange Skinvalut",
    "card_bank_name": "REVOLUT BANK UAB",
    "card_type": "Visa",
    "user_id": 25333341,
    "gate_id": 67,
    "main_requisite": "416598******1337",
    "order_id": 1454995757
  },
  "merchant": {
    "company_id": 128,
    "kam": "Anna",
    "company_name": "GR8",
    "merchant_name": "SUISEN SOLUTIONS LIMITED",
    "merchant_group": "GR8",
    "merchant_id": 243
  },
  "processing": {
    "acquirer_name": "Euroexchange",
    "processor_name": "Euroexchange",
    "processor_id": 67,
    "gate_name": "card"
  },
  "applied_plan": {
    "wl_percent": 6.0,
    "operation_type": "incoming",
    "contract_id": "VSP-281124-2",
    "traffic_type": null,
    "fixed_fee": 0.25,
    "actual_commission": 13.34,
    "exchange_fee_percent": 0.5,
    "plan_key": "VSP-281124-2:incoming:card:4",
    "amount_eur": 261.79,
    "payment_type": "card",
    "tier": null,
    "payout_percent": null,
    "calculated_commission": 15.9574,
    "currency_type": "fiat",
    "chb_fee": 70,
    "refund_fee": 3,
    "card_brand": null,
    "currency": "EUR",
    "region": "EEA",
    "payout_oct_fix": null
  },
  "total_fees": {
    "comission_percent": 5.1,
    "comission_eur": 13.34
  },
  "deviation": {
    "actual": 13.34,
    "calculated": 15.96,
    "difference": -2.62,
    "difference_percent": -16.4
  },
  "commission_fees": {},
  "cost_fees": {},
  "calculation": {
    "type": "sale_eur",
    "description": "Sale (EUR)",
    "formula": "(261.79 x 6.0%) + 0.25",
    "steps": [
      {
        "label": "Amount (EUR)",
        "value": 261.79
      },
      {
        "label": "WL Rate (6.0%)",
        "value": 15.71
      },
      {
        "label": "Fixed Fee",
        "value": 0.25
      },
      {
        "label": "Total",
        "value": 15.96
      }
    ],
    "calculated": 15.96
  }
}