{"transaction":{"transaction_id":"dd12b07f-2328-4fdf-84b4-7ddc4e5e500a","error_message":"Declined by issuer","transaction_status":"declined","created_date_no_time":"2025-12-01","merchant_error_code":22,"transaction_type":"sale","type":"payment","external_error_code":"REFUSED_BY_BANK","merchant_error_message":"DECLINED_BY_ISSUER","external_error_message":"REFUSED_BY_BANK","error_code":9064,"created_date":"2025-12-01 02:31:54.316338 UTC","status":"declined"},"order_details":{"eea":"EEA","country":"DE","bin":null,"running_sum":859228.43,"endpoint_id":70050555,"gate_name":"openbanking","amount_eur":20.0,"fx_date":"2025-12-01","european_union":"EU","card_brand":null,"currency":"EUR","fx_rate":1.0,"requisites_bank":"POSTBANK","card_brand_group":"Any","mapping":"Germany","amount":20.0,"requisites_country":"DE","traffic_type_group":"openbanking","gate_descriptor":"IN - Volt Skunlock Openbanking","card_bank_name":null,"card_type":"Any","user_id":43270187,"gate_id":69,"main_requisite":"DE45100100100308680126","order_id":1455742267},"merchant":{"company_id":12,"kam":"Anna","company_name":"Start2Pay","merchant_name":"Faro Entertainment","merchant_group":"S2P","merchant_id":30},"processing":{"acquirer_name":"Volt","processor_name":"Volt","processor_id":69,"gate_name":"openbanking"},"applied_plan":{"wl_percent":1.5,"operation_type":"incoming","volume_max":null,"contract_id":"VSP-040823-20","traffic_type":null,"fixed_fee":0.3,"actual_commission":0.0,"exchange_fee_percent":0.5,"plan_key":"VSP-040823-20:incoming:apm:13","amount_eur":20.0,"payment_type":"apm","payout_percent":null,"calculated_commission":0.3,"currency_type":"fiat","chb_fee":null,"volume_min":1000001,"refund_fee":1,"card_brand":null,"currency":"EUR","region":"EEA","payout_oct_fix":null},"total_fees":{"comission_percent":0.0,"fixed_eur":null,"comission_eur":0.0,"trx":null},"cost_breakdown":{"mdr_percent":null,"mdr_eur":null,"fixed_eur":null,"agent_eur":null,"trx":null,"base_eur":null,"tax_reserved_eur":0.0,"settle_eur":null},"deviation":{"actual":0,"calculated":0.3,"difference":-0.3,"difference_percent":-100.0},"commission_fees":{},"cost_fees":{},"calculation":{"type":"sale_eur","description":"Sale (EUR)","formula":"(20.00 x 1.5%) + 0.30","steps":[{"label":"Amount (EUR)","value":20.0},{"label":"WL Rate (1.5%)","value":0.3},{"label":"Fixed Fee","value":0.3},{"label":"Total","value":0.6}],"calculated":0.6},"fees":{"comission_percent":0.0,"fixed_eur":null,"comission_eur":0.0,"trx":null}}