{"transaction":{"transaction_id":"dd120e04-0541-47ce-9458-4ea908abe1b0","error_message":"0","transaction_status":"approved","created_date_no_time":"2025-12-11","merchant_error_code":0,"transaction_type":"sale","type":"payment","external_error_code":"0","merchant_error_message":"0","external_error_message":"0","error_code":0,"created_date":"2025-12-11 12:52:59.905106 UTC","status":"approved"},"order_details":{"eea":"EEA","country":"PL","bin":444416129,"running_sum":13800.83,"endpoint_id":70050176,"gate_name":"google_pay","amount_eur":23.65,"fx_date":"2025-12-11","european_union":"EU","card_brand":"VISA","currency":"EUR","fx_rate":1.0,"requisites_bank":null,"card_brand_group":"Visa","mapping":"Poland","amount":23.65,"requisites_country":"PL","traffic_type_group":"google_pay","gate_descriptor":"IN - Xpate Skinvex GooglePay","card_bank_name":"POWSZECHNA KASA OSZCZEDNOSCI BANK POLSKI SA (PKO BANK POLSKI SA)","card_type":"Visa","user_id":42710925,"gate_id":36,"main_requisite":"444416******1667","order_id":1457609194},"merchant":{"company_id":12,"kam":"Anna","company_name":"Start2Pay","merchant_name":"Faro Entertainment","merchant_group":"S2P","merchant_id":30},"processing":{"acquirer_name":"Xpate","processor_name":"Xpate","processor_id":36,"gate_name":"google_pay"},"applied_plan":{"wl_percent":6.0,"operation_type":"incoming","volume_max":null,"contract_id":"VSP-040823-20","traffic_type":null,"fixed_fee":0.15,"actual_commission":1.57,"exchange_fee_percent":0.5,"plan_key":"VSP-040823-20:incoming:apm:15","amount_eur":23.65,"payment_type":"apm","payout_percent":null,"calculated_commission":1.569,"currency_type":"fiat","chb_fee":50,"volume_min":null,"refund_fee":1,"card_brand":null,"currency":"EUR","region":"EEA","payout_oct_fix":null},"total_fees":{"comission_percent":5.37,"fixed_eur":0.3,"comission_eur":1.57,"trx":0.3},"cost_breakdown":{"mdr_percent":3.3,"mdr_eur":0.78045,"fixed_eur":0.3,"agent_eur":null,"trx":0.3,"base_eur":0.78045,"tax_reserved_eur":0.014189999999999998,"settle_eur":null},"deviation":{"actual":1.57,"calculated":1.57,"difference":0.0,"difference_percent":0.1},"commission_fees":{},"cost_fees":{},"calculation":{"type":"sale_eur","description":"Sale (EUR)","formula":"(23.65 x 6.0%) + 0.15","steps":[{"label":"Amount (EUR)","value":23.65},{"label":"WL Rate (6.0%)","value":1.42},{"label":"Fixed Fee","value":0.15},{"label":"Total","value":1.57}],"calculated":1.57},"fees":{"comission_percent":5.37,"fixed_eur":0.3,"comission_eur":1.57,"trx":0.3}}