{"months": ["2025-01", "2025-02", "2025-03", "2025-04", "2025-05", "2025-06", "2025-07", "2025-08", "2025-09", "2025-10", "2025-11", "2025-12"], "plans": [{"plan_id": "70050492_EUR_EEA_WL_IN", "first": "2025-01", "last": "2025-12", "tx_types": ["reversal", "sale"], "counts": {"2025-01": 2, "2025-02": 4310, "2025-03": 6749, "2025-04": 3008, "2025-05": 6816, "2025-06": 31918, "2025-07": 54695, "2025-08": 59111, "2025-09": 67631, "2025-10": 83146, "2025-11": 82924, "2025-12": 35154}, "coverage": {"currencies": ["EUR"], "countries": ["AT", "BE", "BG", "CY", "CZ", "DE", "DK", "EE", "ES", "FI", "FR", "GR", "HR", "HU", "IE", "IS", "IT", "LT", "LU", "MT", "NL", "PL", "PT", "RO", "SE", "SI", "SK"], "gate_types": ["card"]}, "commission": {"avg_rate": 6.22, "min_rate": 4.0, "max_rate": 8.6, "avg_fixed": 0.19, "min_fixed": 0.05, "max_fixed": 0.42}, "monthly_commission": {"2025-02": {"avg_rate": 7.05, "min_rate": 5.95, "max_rate": 8.6, "avg_fixed": 0.15, "min_fixed": 0.15, "max_fixed": 0.3}, "2025-03": {"avg_rate": 7.02, "min_rate": 5.95, "max_rate": 7.55, "avg_fixed": 0.16, "min_fixed": 0.15, "max_fixed": 0.3}, "2025-06": {"avg_rate": 7.0, "min_rate": 4.94, "max_rate": 7.5, "avg_fixed": 0.16, "min_fixed": 0.15, "max_fixed": 0.42}, "2025-07": {"avg_rate": 6.97, "min_rate": 5.5, "max_rate": 7.5, "avg_fixed": 0.16, "min_fixed": 0.15, "max_fixed": 0.35}, "2025-05": {"avg_rate": 7.01, "min_rate": 6.01, "max_rate": 7.5, "avg_fixed": 0.15, "min_fixed": 0.15, "max_fixed": 0.3}, "2025-04": {"avg_rate": 7.01, "min_rate": 6.04, "max_rate": 7.55, "avg_fixed": 0.15, "min_fixed": 0.15, "max_fixed": 0.3}, "2025-09": {"avg_rate": 6.46, "min_rate": 5.07, "max_rate": 7.82, "avg_fixed": 0.16, "min_fixed": 0.05, "max_fixed": 0.35}, "2025-08": {"avg_rate": 6.99, "min_rate": 5.58, "max_rate": 7.86, "avg_fixed": 0.16, "min_fixed": 0.1, "max_fixed": 0.35}, "2025-11": {"avg_rate": 5.18, "min_rate": 4.0, "max_rate": 7.44, "avg_fixed": 0.25, "min_fixed": 0.09, "max_fixed": 0.35}, "2025-10": {"avg_rate": 6.41, "min_rate": 5.0, "max_rate": 7.49, "avg_fixed": 0.17, "min_fixed": 0.09, "max_fixed": 0.35}, "2025-12": {"avg_rate": 5.83, "min_rate": 4.0, "max_rate": 7.6, "avg_fixed": 0.24, "min_fixed": 0.09, "max_fixed": 0.35}}}, {"plan_id": "70050493_EUR_ApplePay_IN", "first": "2025-01", "last": "2025-12", "tx_types": ["reversal", "sale"], "counts": {"2025-01": 0, "2025-02": 3126, "2025-03": 13267, "2025-04": 16860, "2025-05": 17309, "2025-06": 19456, "2025-07": 28930, "2025-08": 34130, "2025-09": 32832, "2025-10": 40497, "2025-11": 45344, "2025-12": 21648}, "coverage": {"currencies": ["EUR"], "countries": ["AE", "AT", "AU", "AZ", "BE", "BG", "BM", "CA", "CH", "CL", "CY", "CZ", "DE", "DK", "EE", "ES", "FR", "GB", "GT", "HK", "HR", "HU", "IE", "IN", "IT", "KE", "KH", "KW", "LI", "LT", "LU", "LV", "MT", "MY", "NL", "NO", "OM", "PL", "RO", "SA", "SK", "TT", "UA", "US", "UY", "VN"], "gate_types": ["apple_pay"]}, "commission": {"avg_rate": 7.43, "min_rate": 4.67, "max_rate": 12.67, "avg_fixed": 0.17, "min_fixed": 0.15, "max_fixed": 0.3}, "monthly_commission": {"2025-03": {"avg_rate": 9.63, "min_rate": 7.06, "max_rate": 12.67, "avg_fixed": 0.15, "min_fixed": 0.15, "max_fixed": 0.15}, "2025-05": {"avg_rate": 9.3, "min_rate": 6.04, "max_rate": 12.67, "avg_fixed": 0.15, "min_fixed": 0.15, "max_fixed": 0.15}, "2025-06": {"avg_rate": 7.79, "min_rate": 6.04, "max_rate": 10.0, "avg_fixed": 0.15, "min_fixed": 0.15, "max_fixed": 0.15}, "2025-04": {"avg_rate": 9.51, "min_rate": 7.06, "max_rate": 12.67, "avg_fixed": 0.15, "min_fixed": 0.15, "max_fixed": 0.15}, "2025-02": {"avg_rate": 9.51, "min_rate": 7.06, "max_rate": 12.67, "avg_fixed": 0.15, "min_fixed": 0.15, "max_fixed": 0.15}, "2025-07": {"avg_rate": 7.75, "min_rate": 6.04, "max_rate": 10.0, "avg_fixed": 0.15, "min_fixed": 0.15, "max_fixed": 0.15}, "2025-11": {"avg_rate": 5.3, "min_rate": 4.67, "max_rate": 6.67, "avg_fixed": 0.21, "min_fixed": 0.15, "max_fixed": 0.3}, "2025-08": {"avg_rate": 7.7, "min_rate": 6.04, "max_rate": 10.0, "avg_fixed": 0.15, "min_fixed": 0.15, "max_fixed": 0.15}, "2025-10": {"avg_rate": 7.52, "min_rate": 5.67, "max_rate": 10.0, "avg_fixed": 0.15, "min_fixed": 0.15, "max_fixed": 0.3}, "2025-09": {"avg_rate": 7.71, "min_rate": 6.04, "max_rate": 10.0, "avg_fixed": 0.15, "min_fixed": 0.15, "max_fixed": 0.15}, "2025-12": {"avg_rate": 5.86, "min_rate": 4.67, "max_rate": 6.67, "avg_fixed": 0.22, "min_fixed": 0.15, "max_fixed": 0.3}}}, {"plan_id": "70050494_EUR_GooglePay_IN", "first": "2025-01", "last": "2025-12", "tx_types": ["sale"], "counts": {"2025-01": 0, "2025-02": 1166, "2025-03": 4296, "2025-04": 5814, "2025-05": 5822, "2025-06": 6993, "2025-07": 7040, "2025-08": 7830, "2025-09": 6876, "2025-10": 7193, "2025-11": 7290, "2025-12": 3506}, "coverage": {"currencies": ["EUR"], "countries": ["AE", "AT", "BE", "BG", "CA", "CH", "CZ", "DE", "DK", "DO", "EE", "ES", "FR", "GB", "HR", "HU", "IE", "IN", "IT", "JP", "KH", "KW", "LI", "LT", "LU", "LV", "MY", "NL", "NZ", "OM", "PL", "QA", "RO", "RS", "SE", "SG", "SK", "TT", "TW", "UA", "US", "UY", "ZA"], "gate_types": ["google_pay"]}, "commission": {"avg_rate": 7.61, "min_rate": 4.67, "max_rate": 11.67, "avg_fixed": 0.28, "min_fixed": 0.15, "max_fixed": 0.3}, "monthly_commission": {"2025-02": {"avg_rate": 9.39, "min_rate": 7.05, "max_rate": 11.67, "avg_fixed": 0.3, "min_fixed": 0.3, "max_fixed": 0.3}, "2025-03": {"avg_rate": 9.5, "min_rate": 7.11, "max_rate": 11.67, "avg_fixed": 0.3, "min_fixed": 0.3, "max_fixed": 0.3}, "2025-05": {"avg_rate": 8.91, "min_rate": 6.05, "max_rate": 11.67, "avg_fixed": 0.3, "min_fixed": 0.15, "max_fixed": 0.3}, "2025-06": {"avg_rate": 7.44, "min_rate": 6.03, "max_rate": 10.0, "avg_fixed": 0.29, "min_fixed": 0.15, "max_fixed": 0.3}, "2025-04": {"avg_rate": 9.25, "min_rate": 7.05, "max_rate": 11.67, "avg_fixed": 0.3, "min_fixed": 0.3, "max_fixed": 0.3}, "2025-07": {"avg_rate": 7.46, "min_rate": 6.04, "max_rate": 10.0, "avg_fixed": 0.27, "min_fixed": 0.15, "max_fixed": 0.3}, "2025-09": {"avg_rate": 7.39, "min_rate": 6.03, "max_rate": 10.0, "avg_fixed": 0.27, "min_fixed": 0.15, "max_fixed": 0.3}, "2025-08": {"avg_rate": 7.38, "min_rate": 6.03, "max_rate": 10.0, "avg_fixed": 0.27, "min_fixed": 0.15, "max_fixed": 0.3}, "2025-11": {"avg_rate": 5.08, "min_rate": 4.67, "max_rate": 6.67, "avg_fixed": 0.26, "min_fixed": 0.15, "max_fixed": 0.3}, "2025-10": {"avg_rate": 7.31, "min_rate": 5.67, "max_rate": 10.0, "avg_fixed": 0.25, "min_fixed": 0.15, "max_fixed": 0.3}, "2025-12": {"avg_rate": 5.71, "min_rate": 4.67, "max_rate": 6.67, "avg_fixed": 0.27, "min_fixed": 0.15, "max_fixed": 0.3}}}, {"plan_id": "70050495_PLN_Blik_IN", "first": "2025-01", "last": "2025-09", "tx_types": ["sale"], "counts": {"2025-01": 1, "2025-02": 1, "2025-07": 1, "2025-09": 0}, "coverage": {"currencies": ["PLN"], "countries": ["PL"], "gate_types": ["blik"]}, "commission": {"avg_rate": 15.37, "min_rate": 8.12, "max_rate": 19.0, "avg_fixed": 0.1, "min_fixed": 0.09, "max_fixed": 0.1}, "monthly_commission": {"2025-07": {"avg_rate": 8.12, "min_rate": 8.12, "max_rate": 8.12, "avg_fixed": 0.1, "min_fixed": 0.1, "max_fixed": 0.1}, "2025-01": {"avg_rate": 19.0, "min_rate": 19.0, "max_rate": 19.0, "avg_fixed": 0.09, "min_fixed": 0.09, "max_fixed": 0.09}, "2025-02": {"avg_rate": 19.0, "min_rate": 19.0, "max_rate": 19.0, "avg_fixed": 0.1, "min_fixed": 0.1, "max_fixed": 0.1}}}, {"plan_id": "70050492_EUR_OUT", "first": "2025-02", "last": "2025-12", "tx_types": ["payout"], "counts": {"2025-02": 13, "2025-03": 174, "2025-04": 2229, "2025-05": 2334, "2025-06": 5596, "2025-07": 10146, "2025-08": 10009, "2025-09": 19927, "2025-10": 19090, "2025-11": 19914, "2025-12": 8887}, "coverage": {"currencies": ["EUR"], "countries": ["AT", "BE", "BG", "CH", "CY", "CZ", "DE", "DK", "EE", "ES", "FI", "FR", "GB", "GR", "HR", "HU", "IE", "IS", "IT", "KZ", "LT", "LU", "MK", "MN", "MT", "NL", "PL", "RO", "SE", "SK"], "gate_types": ["card"]}, "commission": {"avg_rate": 4.21, "min_rate": 1.5, "max_rate": 29.6, "avg_fixed": 0.46, "min_fixed": 0.1, "max_fixed": 1.0}, "monthly_commission": {"2025-05": {"avg_rate": 5.13, "min_rate": 3.52, "max_rate": 10.0, "avg_fixed": 0.77, "min_fixed": 0.5, "max_fixed": 1.0}, "2025-06": {"avg_rate": 4.38, "min_rate": 3.52, "max_rate": 7.05, "avg_fixed": 0.79, "min_fixed": 0.5, "max_fixed": 1.0}, "2025-04": {"avg_rate": 5.55, "min_rate": 4.03, "max_rate": 11.32, "avg_fixed": 0.79, "min_fixed": 0.2, "max_fixed": 1.0}, "2025-02": {"avg_rate": 5.02, "min_rate": 4.2, "max_rate": 6.73, "avg_fixed": 0.75, "min_fixed": 0.5, "max_fixed": 0.8}, "2025-03": {"avg_rate": 5.65, "min_rate": 4.04, "max_rate": 13.03, "avg_fixed": 0.76, "min_fixed": 0.2, "max_fixed": 1.0}, "2025-07": {"avg_rate": 4.43, "min_rate": 3.53, "max_rate": 8.5, "avg_fixed": 0.75, "min_fixed": 0.5, "max_fixed": 0.8}, "2025-09": {"avg_rate": 4.81, "min_rate": 3.53, "max_rate": 10.5, "avg_fixed": 0.44, "min_fixed": 0.1, "max_fixed": 0.8}, "2025-11": {"avg_rate": 3.27, "min_rate": 1.5, "max_rate": 5.11, "avg_fixed": 0.29, "min_fixed": 0.1, "max_fixed": 0.8}, "2025-10": {"avg_rate": 4.89, "min_rate": 2.42, "max_rate": 29.6, "avg_fixed": 0.27, "min_fixed": 0.1, "max_fixed": 0.8}, "2025-08": {"avg_rate": 4.44, "min_rate": 3.53, "max_rate": 8.5, "avg_fixed": 0.74, "min_fixed": 0.5, "max_fixed": 0.8}, "2025-12": {"avg_rate": 3.12, "min_rate": 1.5, "max_rate": 5.57, "avg_fixed": 0.4, "min_fixed": 0.1, "max_fixed": 0.8}}}, {"plan_id": "70050492_EUR_ROW_WL_IN", "first": "2025-02", "last": "2025-12", "tx_types": ["sale"], "counts": {"2025-02": 43, "2025-03": 68, "2025-04": 32, "2025-05": 78, "2025-06": 208, "2025-07": 314, "2025-08": 332, "2025-09": 383, "2025-10": 692, "2025-11": 658, "2025-12": 167}, "coverage": {"currencies": ["EUR"], "countries": ["AE", "AG", "AM", "CA", "CH", "CL", "GB", "HK", "IL", "IN", "KR", "KZ", "MK", "MN", "MY", "PH", "PS", "RS", "SG", "TW", "UY"], "gate_types": ["card"]}, "commission": {"avg_rate": 7.17, "min_rate": 6.09, "max_rate": 8.55, "avg_fixed": 0.22, "min_fixed": 0.09, "max_fixed": 0.35}, "monthly_commission": {"2025-03": {"avg_rate": 8.04, "min_rate": 7.6, "max_rate": 8.53, "avg_fixed": 0.15, "min_fixed": 0.15, "max_fixed": 0.15}, "2025-06": {"avg_rate": 7.22, "min_rate": 6.57, "max_rate": 7.88, "avg_fixed": 0.2, "min_fixed": 0.15, "max_fixed": 0.3}, "2025-05": {"avg_rate": 7.71, "min_rate": 7.04, "max_rate": 8.28, "avg_fixed": 0.15, "min_fixed": 0.15, "max_fixed": 0.3}, "2025-09": {"avg_rate": 7.13, "min_rate": 6.1, "max_rate": 8.0, "avg_fixed": 0.22, "min_fixed": 0.1, "max_fixed": 0.35}, "2025-08": {"avg_rate": 7.18, "min_rate": 6.5, "max_rate": 7.78, "avg_fixed": 0.22, "min_fixed": 0.15, "max_fixed": 0.3}, "2025-07": {"avg_rate": 7.17, "min_rate": 6.52, "max_rate": 7.93, "avg_fixed": 0.22, "min_fixed": 0.15, "max_fixed": 0.3}, "2025-11": {"avg_rate": 7.04, "min_rate": 6.22, "max_rate": 8.41, "avg_fixed": 0.24, "min_fixed": 0.09, "max_fixed": 0.35}, "2025-10": {"avg_rate": 7.13, "min_rate": 6.09, "max_rate": 8.34, "avg_fixed": 0.22, "min_fixed": 0.09, "max_fixed": 0.35}, "2025-02": {"avg_rate": 8.25, "min_rate": 7.61, "max_rate": 8.55, "avg_fixed": 0.15, "min_fixed": 0.15, "max_fixed": 0.15}, "2025-12": {"avg_rate": 7.1, "min_rate": 6.5, "max_rate": 7.86, "avg_fixed": 0.23, "min_fixed": 0.15, "max_fixed": 0.3}, "2025-04": {"avg_rate": 7.59, "min_rate": 7.0, "max_rate": 8.15, "avg_fixed": 0.18, "min_fixed": 0.15, "max_fixed": 0.3}}}, {"plan_id": "70050499_EUR_SEPA_OUT", "first": "2025-02", "last": "2025-12", "tx_types": ["payout"], "counts": {"2025-02": 42, "2025-03": 273, "2025-04": 336, "2025-05": 533, "2025-06": 924, "2025-07": 968, "2025-08": 1005, "2025-09": 1072, "2025-10": 1456, "2025-11": 1457, "2025-12": 731}, "coverage": {"currencies": ["EUR"], "countries": ["AT", "BE", "CH", "CZ", "DE", "DK", "ES", "GB", "HU", "HV", "IE", "IT", "LT", "NL", "PL", "RO", "SK", "TR", "UA"], "gate_types": ["sepa"]}, "commission": {"avg_rate": 1.9, "min_rate": 1.51, "max_rate": 4.99, "avg_fixed": 0.9, "min_fixed": 0.7, "max_fixed": 1.0}, "monthly_commission": {"2025-03": {"avg_rate": 1.73, "min_rate": 1.52, "max_rate": 4.0, "avg_fixed": 1.0, "min_fixed": 1.0, "max_fixed": 1.0}, "2025-06": {"avg_rate": 1.58, "min_rate": 1.52, "max_rate": 2.2, "avg_fixed": 0.98, "min_fixed": 0.8, "max_fixed": 1.0}, "2025-05": {"avg_rate": 1.54, "min_rate": 1.52, "max_rate": 1.57, "avg_fixed": 0.87, "min_fixed": 0.8, "max_fixed": 1.0}, "2025-07": {"avg_rate": 2.27, "min_rate": 1.52, "max_rate": 4.99, "avg_fixed": 0.81, "min_fixed": 0.8, "max_fixed": 1.0}, "2025-04": {"avg_rate": 1.58, "min_rate": 1.52, "max_rate": 2.21, "avg_fixed": 1.0, "min_fixed": 1.0, "max_fixed": 1.0}, "2025-10": {"avg_rate": 2.41, "min_rate": 1.52, "max_rate": 3.32, "avg_fixed": 0.8, "min_fixed": 0.8, "max_fixed": 0.8}, "2025-09": {"avg_rate": 2.29, "min_rate": 1.62, "max_rate": 3.59, "avg_fixed": 0.77, "min_fixed": 0.7, "max_fixed": 0.8}, "2025-02": {"avg_rate": 1.53, "min_rate": 1.53, "max_rate": 1.53, "avg_fixed": 1.0, "min_fixed": 1.0, "max_fixed": 1.0}, "2025-12": {"avg_rate": 1.51, "min_rate": 1.51, "max_rate": 1.51, "avg_fixed": 1.0, "min_fixed": 1.0, "max_fixed": 1.0}}}, {"plan_id": "70050595_EUR_SOFORT_EEA_WL_IN", "first": "2025-05", "last": "2025-06", "tx_types": ["sale"], "counts": {"2025-05": 1, "2025-06": 0}, "coverage": {"currencies": ["EUR"], "countries": ["DE", "HU", "PL"], "gate_types": ["sofort"]}, "commission": {"avg_rate": 8.8, "min_rate": 8.8, "max_rate": 8.8, "avg_fixed": 0.39, "min_fixed": 0.39, "max_fixed": 0.39}, "monthly_commission": {"2025-05": {"avg_rate": 8.8, "min_rate": 8.8, "max_rate": 8.8, "avg_fixed": 0.39, "min_fixed": 0.39, "max_fixed": 0.39}}}, {"plan_id": "70050598_EUR_Open_Banking_IN", "first": "2025-05", "last": "2025-12", "tx_types": ["sale"], "counts": {"2025-05": 0, "2025-06": 322, "2025-07": 512, "2025-08": 567, "2025-09": 388, "2025-10": 463, "2025-11": 1109, "2025-12": 534}, "coverage": {"currencies": ["EUR"], "countries": ["AT", "BE", "DE", "HU", "IT", "LT", "NL", "PL", "SK"], "gate_types": ["openbanking"]}, "commission": {"avg_rate": 6.91, "min_rate": 3.04, "max_rate": 11.5, "avg_fixed": 0.16, "min_fixed": 0.15, "max_fixed": 0.25}, "monthly_commission": {"2025-06": {"avg_rate": 6.11, "min_rate": 3.08, "max_rate": 10.5, "avg_fixed": 0.25, "min_fixed": 0.25, "max_fixed": 0.25}, "2025-09": {"avg_rate": 6.69, "min_rate": 3.07, "max_rate": 11.5, "avg_fixed": 0.15, "min_fixed": 0.15, "max_fixed": 0.15}, "2025-07": {"avg_rate": 6.93, "min_rate": 3.09, "max_rate": 11.5, "avg_fixed": 0.15, "min_fixed": 0.15, "max_fixed": 0.15}, "2025-08": {"avg_rate": 7.28, "min_rate": 3.28, "max_rate": 11.5, "avg_fixed": 0.15, "min_fixed": 0.15, "max_fixed": 0.15}, "2025-11": {"avg_rate": 7.09, "min_rate": 3.06, "max_rate": 11.5, "avg_fixed": 0.15, "min_fixed": 0.15, "max_fixed": 0.15}, "2025-10": {"avg_rate": 6.93, "min_rate": 3.08, "max_rate": 11.5, "avg_fixed": 0.15, "min_fixed": 0.15, "max_fixed": 0.15}, "2025-12": {"avg_rate": 6.73, "min_rate": 3.04, "max_rate": 11.5, "avg_fixed": 0.15, "min_fixed": 0.15, "max_fixed": 0.15}}}], "month_meta": {"2025-01": {"currencies": ["EUR", "PLN"], "countries": [{"code": "LT", "count": 2}, {"code": "PL", "count": 1}], "gate_types": ["blik", "card"]}, "2025-02": {"currencies": ["EUR", "PLN"], "countries": [{"code": "HU", "count": 8263}, {"code": "PL", "count": 255}, {"code": "DE", "count": 40}, {"code": "IT", "count": 38}, {"code": "AT", "count": 30}, {"code": "CH", "count": 29}, {"code": "GB", "count": 15}, {"code": "SK", "count": 8}, {"code": "LT", "count": 5}, {"code": "FI", "count": 4}, {"code": "RO", "count": 4}, {"code": "NL", "count": 3}, {"code": "BE", "count": 3}, {"code": "IE", "count": 2}, {"code": "CZ", "count": 1}, {"code": "BG", "count": 1}, {"code": "AG", "count": 0}], "gate_types": ["apple_pay", "blik", "card", "google_pay", "sepa"]}, "2025-03": {"currencies": ["EUR"], "countries": [{"code": "HU", "count": 19655}, {"code": "GB", "count": 2043}, {"code": "US", "count": 834}, {"code": "PL", "count": 604}, {"code": "AT", "count": 324}, {"code": "HR", "count": 284}, {"code": "OM", "count": 282}, {"code": "IT", "count": 199}, {"code": "DE", "count": 169}, {"code": "KW", "count": 115}, {"code": "UY", "count": 66}, {"code": "CH", "count": 64}, {"code": "KH", "count": 27}, {"code": "LT", "count": 26}, {"code": "UA", "count": 20}, {"code": "FR", "count": 20}, {"code": "TT", "count": 20}, {"code": "MY", "count": 13}, {"code": "BE", "count": 10}, {"code": "NL", "count": 9}, {"code": "RO", "count": 9}, {"code": "IE", "count": 7}, {"code": "FI", "count": 6}, {"code": "SK", "count": 5}, {"code": "CA", "count": 5}, {"code": "CZ", "count": 5}, {"code": "AZ", "count": 3}, {"code": "GT", "count": 1}, {"code": "ES", "count": 1}, {"code": "DK", "count": 1}, {"code": "NO", "count": 0}], "gate_types": ["apple_pay", "card", "google_pay", "sepa"]}, "2025-04": {"currencies": ["EUR"], "countries": [{"code": "HU", "count": 20277}, {"code": "GB", "count": 3281}, {"code": "US", "count": 1488}, {"code": "HR", "count": 610}, {"code": "PL", "count": 560}, {"code": "AT", "count": 430}, {"code": "OM", "count": 330}, {"code": "IT", "count": 304}, {"code": "DE", "count": 236}, {"code": "TT", "count": 156}, {"code": "CH", "count": 133}, {"code": "KW", "count": 89}, {"code": "SK", "count": 70}, {"code": "FR", "count": 55}, {"code": "LT", "count": 54}, {"code": "KH", "count": 44}, {"code": "UY", "count": 41}, {"code": "IE", "count": 25}, {"code": "MY", "count": 19}, {"code": "ES", "count": 14}, {"code": "NL", "count": 14}, {"code": "KE", "count": 11}, {"code": "GT", "count": 8}, {"code": "BE", "count": 8}, {"code": "RO", "count": 8}, {"code": "CA", "count": 6}, {"code": "CZ", "count": 3}, {"code": "UA", "count": 1}, {"code": "EE", "count": 1}, {"code": "LV", "count": 1}, {"code": "AZ", "count": 1}, {"code": "CY", "count": 1}, {"code": "AU", "count": 0}, {"code": "NO", "count": 0}, {"code": "VN", "count": 0}], "gate_types": ["apple_pay", "card", "google_pay", "sepa"]}, "2025-05": {"currencies": ["EUR"], "countries": [{"code": "HU", "count": 19866}, {"code": "GB", "count": 4435}, {"code": "US", "count": 3104}, {"code": "AT", "count": 813}, {"code": "IT", "count": 801}, {"code": "DE", "count": 702}, {"code": "HR", "count": 621}, {"code": "CH", "count": 523}, {"code": "IE", "count": 333}, {"code": "OM", "count": 326}, {"code": "UY", "count": 267}, {"code": "SK", "count": 227}, {"code": "TT", "count": 154}, {"code": "KW", "count": 140}, {"code": "UA", "count": 91}, {"code": "LV", "count": 78}, {"code": "LT", "count": 69}, {"code": "BE", "count": 56}, {"code": "FR", "count": 34}, {"code": "CA", "count": 33}, {"code": "ES", "count": 31}, {"code": "CZ", "count": 27}, {"code": "KH", "count": 26}, {"code": "MY", "count": 25}, {"code": "JP", "count": 15}, {"code": "PL", "count": 14}, {"code": "NZ", "count": 14}, {"code": "DO", "count": 12}, {"code": "SG", "count": 11}, {"code": "NL", "count": 11}, {"code": "RO", "count": 7}, {"code": "KE", "count": 6}, {"code": "CY", "count": 6}, {"code": "FI", "count": 5}, {"code": "DK", "count": 3}, {"code": "GT", "count": 1}, {"code": "IN", "count": 1}, {"code": "KZ", "count": 1}, {"code": "TW", "count": 1}, {"code": "QA", "count": 1}, {"code": "SE", "count": 1}, {"code": "BG", "count": 1}], "gate_types": ["apple_pay", "card", "google_pay", "sepa", "sofort"]}, "2025-06": {"currencies": ["EUR"], "countries": [{"code": "HU", "count": 49303}, {"code": "GB", "count": 5481}, {"code": "US", "count": 2286}, {"code": "DE", "count": 1985}, {"code": "IT", "count": 1354}, {"code": "CH", "count": 1093}, {"code": "AT", "count": 674}, {"code": "IE", "count": 605}, {"code": "HR", "count": 503}, {"code": "UY", "count": 309}, {"code": "OM", "count": 204}, {"code": "SK", "count": 188}, {"code": "TT", "count": 166}, {"code": "LV", "count": 162}, {"code": "KW", "count": 130}, {"code": "UA", "count": 125}, {"code": "LT", "count": 119}, {"code": "BE", "count": 102}, {"code": "ES", "count": 85}, {"code": "FR", "count": 72}, {"code": "RO", "count": 67}, {"code": "PL", "count": 57}, {"code": "NL", "count": 39}, {"code": "KH", "count": 39}, {"code": "SG", "count": 32}, {"code": "CA", "count": 30}, {"code": "MY", "count": 29}, {"code": "JP", "count": 28}, {"code": "CZ", "count": 28}, {"code": "FI", "count": 26}, {"code": "DO", "count": 25}, {"code": "DK", "count": 20}, {"code": "NZ", "count": 10}, {"code": "SE", "count": 8}, {"code": "LU", "count": 5}, {"code": "BG", "count": 5}, {"code": "BM", "count": 5}, {"code": "MT", "count": 4}, {"code": "CL", "count": 3}, {"code": "AE", "count": 3}, {"code": "GT", "count": 2}, {"code": "SA", "count": 2}, {"code": "TW", "count": 2}, {"code": "IN", "count": 1}, {"code": "IS", "count": 1}, {"code": "EE", "count": 0}, {"code": "KZ", "count": 0}, {"code": "AM", "count": 0}, {"code": "TR", "count": 0}], "gate_types": ["apple_pay", "card", "google_pay", "openbanking", "sepa"]}, "2025-07": {"currencies": ["EUR", "PLN"], "countries": [{"code": "HU", "count": 90987}, {"code": "DE", "count": 3439}, {"code": "IT", "count": 2408}, {"code": "AT", "count": 1906}, {"code": "GB", "count": 1619}, {"code": "CH", "count": 571}, {"code": "US", "count": 374}, {"code": "SK", "count": 220}, {"code": "NL", "count": 206}, {"code": "LT", "count": 156}, {"code": "RO", "count": 114}, {"code": "IE", "count": 113}, {"code": "KW", "count": 94}, {"code": "HR", "count": 89}, {"code": "BE", "count": 47}, {"code": "OM", "count": 46}, {"code": "BG", "count": 29}, {"code": "TT", "count": 25}, {"code": "PL", "count": 24}, {"code": "ES", "count": 22}, {"code": "UY", "count": 20}, {"code": "IS", "count": 16}, {"code": "FR", "count": 14}, {"code": "DK", "count": 14}, {"code": "CA", "count": 10}, {"code": "FI", "count": 8}, {"code": "EE", "count": 8}, {"code": "CZ", "count": 7}, {"code": "GR", "count": 5}, {"code": "MT", "count": 3}, {"code": "KH", "count": 3}, {"code": "UA", "count": 2}, {"code": "LU", "count": 2}, {"code": "SA", "count": 2}, {"code": "MY", "count": 2}, {"code": "SE", "count": 1}, {"code": "SG", "count": 0}, {"code": "PT", "count": 0}, {"code": "LI", "count": 0}], "gate_types": ["apple_pay", "blik", "card", "google_pay", "openbanking", "sepa"]}, "2025-08": {"currencies": ["EUR"], "countries": [{"code": "HU", "count": 101937}, {"code": "DE", "count": 4753}, {"code": "IT", "count": 2484}, {"code": "AT", "count": 1814}, {"code": "CH", "count": 491}, {"code": "SK", "count": 334}, {"code": "NL", "count": 314}, {"code": "RO", "count": 246}, {"code": "LT", "count": 191}, {"code": "GB", "count": 154}, {"code": "IE", "count": 87}, {"code": "EE", "count": 36}, {"code": "FR", "count": 23}, {"code": "LU", "count": 16}, {"code": "ES", "count": 15}, {"code": "BE", "count": 15}, {"code": "CZ", "count": 13}, {"code": "PL", "count": 12}, {"code": "DK", "count": 10}, {"code": "HR", "count": 9}, {"code": "BG", "count": 7}, {"code": "IS", "count": 6}, {"code": "AE", "count": 6}, {"code": "HK", "count": 4}, {"code": "GR", "count": 3}, {"code": "RS", "count": 2}, {"code": "MN", "count": 2}, {"code": "UA", "count": 0}, {"code": "CL", "count": 0}, {"code": "SE", "count": 0}, {"code": "PH", "count": 0}, {"code": "CY", "count": 0}], "gate_types": ["apple_pay", "card", "google_pay", "openbanking", "sepa"]}, "2025-09": {"currencies": ["EUR"], "countries": [{"code": "HU", "count": 117271}, {"code": "DE", "count": 4458}, {"code": "IT", "count": 2812}, {"code": "AT", "count": 1878}, {"code": "RO", "count": 619}, {"code": "CH", "count": 609}, {"code": "NL", "count": 494}, {"code": "SK", "count": 317}, {"code": "LT", "count": 232}, {"code": "IE", "count": 114}, {"code": "GB", "count": 97}, {"code": "ES", "count": 33}, {"code": "FR", "count": 32}, {"code": "BG", "count": 30}, {"code": "CZ", "count": 24}, {"code": "ZA", "count": 14}, {"code": "BE", "count": 13}, {"code": "IS", "count": 11}, {"code": "EE", "count": 10}, {"code": "DK", "count": 10}, {"code": "PL", "count": 6}, {"code": "HR", "count": 5}, {"code": "HK", "count": 5}, {"code": "FI", "count": 4}, {"code": "AE", "count": 4}, {"code": "MT", "count": 3}, {"code": "LU", "count": 2}, {"code": "LI", "count": 2}, {"code": "UA", "count": 0}, {"code": "PS", "count": 0}, {"code": "RS", "count": 0}, {"code": "GR", "count": 0}, {"code": "MN", "count": 0}], "gate_types": ["apple_pay", "card", "google_pay", "openbanking", "sepa"]}, "2025-10": {"currencies": ["EUR"], "countries": [{"code": "HU", "count": 136729}, {"code": "DE", "count": 6725}, {"code": "IT", "count": 3430}, {"code": "AT", "count": 2364}, {"code": "CH", "count": 1205}, {"code": "SK", "count": 525}, {"code": "NL", "count": 399}, {"code": "GB", "count": 255}, {"code": "RO", "count": 243}, {"code": "LT", "count": 237}, {"code": "PL", "count": 122}, {"code": "IE", "count": 83}, {"code": "BE", "count": 47}, {"code": "ES", "count": 37}, {"code": "IS", "count": 27}, {"code": "DK", "count": 24}, {"code": "EE", "count": 21}, {"code": "FR", "count": 14}, {"code": "CZ", "count": 12}, {"code": "MK", "count": 9}, {"code": "SE", "count": 6}, {"code": "BG", "count": 5}, {"code": "LU", "count": 4}, {"code": "UA", "count": 3}, {"code": "ZA", "count": 3}, {"code": "CY", "count": 3}, {"code": "MT", "count": 2}, {"code": "AE", "count": 2}, {"code": "HR", "count": 1}, {"code": "IL", "count": 0}, {"code": "TW", "count": 0}, {"code": "KR", "count": 0}, {"code": "GR", "count": 0}, {"code": "PT", "count": 0}], "gate_types": ["apple_pay", "card", "google_pay", "openbanking", "sepa"]}, "2025-11": {"currencies": ["EUR"], "countries": [{"code": "HU", "count": 141404}, {"code": "DE", "count": 7519}, {"code": "IT", "count": 3424}, {"code": "AT", "count": 2485}, {"code": "CH", "count": 1068}, {"code": "SK", "count": 820}, {"code": "LT", "count": 606}, {"code": "NL", "count": 494}, {"code": "GB", "count": 238}, {"code": "BE", "count": 193}, {"code": "RO", "count": 130}, {"code": "ES", "count": 64}, {"code": "PL", "count": 49}, {"code": "FI", "count": 33}, {"code": "SE", "count": 25}, {"code": "CZ", "count": 24}, {"code": "DK", "count": 23}, {"code": "BG", "count": 20}, {"code": "LU", "count": 19}, {"code": "IE", "count": 18}, {"code": "FR", "count": 15}, {"code": "EE", "count": 14}, {"code": "IS", "count": 5}, {"code": "MT", "count": 4}, {"code": "HK", "count": 2}, {"code": "UA", "count": 0}, {"code": "IN", "count": 0}, {"code": "SI", "count": 0}, {"code": "KR", "count": 0}, {"code": "HR", "count": 0}, {"code": "PT", "count": 0}, {"code": "MK", "count": 0}, {"code": "PH", "count": 0}], "gate_types": ["apple_pay", "card", "google_pay", "openbanking", "sepa"]}, "2025-12": {"currencies": ["EUR"], "countries": [{"code": "HU", "count": 63018}, {"code": "DE", "count": 3670}, {"code": "IT", "count": 1361}, {"code": "AT", "count": 1075}, {"code": "SK", "count": 380}, {"code": "LT", "count": 346}, {"code": "CH", "count": 271}, {"code": "NL", "count": 143}, {"code": "BE", "count": 105}, {"code": "GB", "count": 92}, {"code": "RO", "count": 66}, {"code": "ES", "count": 21}, {"code": "FI", "count": 14}, {"code": "LU", "count": 11}, {"code": "PL", "count": 10}, {"code": "IE", "count": 9}, {"code": "DK", "count": 9}, {"code": "EE", "count": 8}, {"code": "SE", "count": 7}, {"code": "CZ", "count": 5}, {"code": "FR", "count": 5}, {"code": "HR", "count": 1}, {"code": "CA", "count": 0}, {"code": "IS", "count": 0}, {"code": "KR", "count": 0}, {"code": "TW", "count": 0}, {"code": "CL", "count": 0}, {"code": "MY", "count": 0}, {"code": "BG", "count": 0}, {"code": "UY", "count": 0}, {"code": "HV", "count": 0}], "gate_types": ["apple_pay", "card", "google_pay", "openbanking", "sepa"]}}}